pdpcli/__init__.py
pdpcli/__main__.py
pdpcli/commands/__init__.py
pdpcli/commands/apply.py
pdpcli/commands/build.py
pdpcli/commands/subcommand.py
pdpcli/configs/__init__.py
pdpcli/configs/config_builder.py
pdpcli/configs/config_readers.py
pdpcli/configs/jsonnet.py
pdpcli/data/__init__.py
pdpcli/data/data_readers.py
pdpcli/data/data_writers.py
pdpcli/exceptions.py
pdpcli/plugins.py
pdpcli/py.typed
pdpcli/registrable.py
pdpcli/settings.py
pdpcli/stages/__init__.py
pdpcli/stages/pass_through_stage.py
pdpcli/stages/pdpipe.py
pdpcli/stages/pipeline.py
pdpcli/stages/select_columns.py
pdpcli/stages/sklearn_stages.py
pdpcli/stages/stage.py
pdpcli/util.py
pdpcli-0.4.1.dist-info/entry_points.txt
pdpcli-0.4.1.dist-info/LICENSE
pdpcli-0.4.1.dist-info/WHEEL
pdpcli-0.4.1.dist-info/METADATA
pdpcli-0.4.1.dist-info/RECORD
