Metadata-Version: 2.1
Name: pdpcli
Version: 0.4.1
Summary: PdpCLI is a pandas DataFrame processing CLI tool which enables you to build a pandas pipeline from a configuration file.
Home-page: https://github.com/altescy/pdpcli
License: MIT
Keywords: python,cli,pandas,csv
Author: altescy
Author-email: altescy@fastmail.com
Requires-Python: >=3.8,<4.0
Classifier: Development Status :: 3 - Alpha
Classifier: License :: OSI Approved :: MIT License
Classifier: Programming Language :: Python :: 3
Classifier: Programming Language :: Python :: 3.8
Classifier: Programming Language :: Python :: 3.9
Provides-Extra: all
Provides-Extra: mysql
Provides-Extra: pgsql
Requires-Dist: colt (>=0.7.1,<0.8.0)
Requires-Dist: jsonnet (>=0.17.0,<0.18.0)
Requires-Dist: minato[all] (>=0.6.0,<0.7.0)
Requires-Dist: mysqlclient (>=2.0.3,<3.0.0); extra == "mysql" or extra == "all"
Requires-Dist: nltk (>=3.5,<4.0)
Requires-Dist: omegaconf (>=2.0.6,<3.0.0)
Requires-Dist: pandas (>=1.2.2,<2.0.0)
Requires-Dist: pdpipe (>=0.0.53,<0.0.54)
Requires-Dist: psycopg2 (>=2.8.6,<3.0.0); extra == "pgsql" or extra == "all"
Requires-Dist: scikit-learn (>=0.24.1,<0.25.0)
Requires-Dist: sqlalchemy (>=1.3.23,<2.0.0)
